<annotations><filename>GH020005_025.jpg</filename><folder>images</folder><size><width>640</width><height>480</height><depth>3</depth></size><object><name>Head</name><pose>Unspecified</pose><truncated>0</truncated><difficult>0</difficult><bndbox><xmin>440.49984</xmin><ymin>54.66672</ymin><xmax>467.50016</xmax><ymax>84.66672</ymax></bndbox></object><object><name>Body</name><pose>Unspecified</pose><truncated>0</truncated><difficult>0</difficult><bndbox><xmin>398.49952</xmin><ymin>84.66672</ymin><xmax>467.49984</xmax><ymax>165.33360000000002</ymax></bndbox></object><object><name>Person</name><pose>Unspecified</pose><truncated>0</truncated><difficult>0</difficult><bndbox><xmin>388.50016</xmin><ymin>48.66672</ymin><xmax>481.50048</xmax><ymax>180.66672</ymax></bndbox></object><object><name>Car_1</name><pose>Unspecified</pose><truncated>0</truncated><difficult>0</difficult><bndbox><xmin>239.99967999999998</xmin><ymin>17.99976000000001</ymin><xmax>527.49984</xmax><ymax>288.66648</ymax></bndbox></object></annotations>