<annotations><filename>GH020005_010.jpg</filename><folder>images</folder><size><width>640</width><height>480</height><depth>3</depth></size><object><name>Person</name><pose>Unspecified</pose><truncated>0</truncated><difficult>0</difficult><bndbox><xmin>540.0</xmin><ymin>72.66648</ymin><xmax>578.49984</xmax><ymax>146.66664</ymax></bndbox></object><object><name>Head</name><pose>Unspecified</pose><truncated>0</truncated><difficult>0</difficult><bndbox><xmin>555.49984</xmin><ymin>74.66687999999999</ymin><xmax>569.49984</xmax><ymax>92.66687999999999</ymax></bndbox></object><object><name>Body</name><pose>Unspecified</pose><truncated>0</truncated><difficult>0</difficult><bndbox><xmin>542.5001599999999</xmin><ymin>96.66672</ymin><xmax>574.00032</xmax><ymax>138.66672</ymax></bndbox></object></annotations>