<annotations><filename>GH020005_704.jpg</filename><folder>images</folder><size><width>640</width><height>480</height><depth>3</depth></size><object><name>Car_1</name><pose>Unspecified</pose><truncated>0</truncated><difficult>0</difficult><bndbox><xmin>547.5001599999999</xmin><ymin>57.333119999999994</ymin><xmax>602.50048</xmax><ymax>141.33312</ymax></bndbox></object><object><name>Car_1</name><pose>Unspecified</pose><truncated>0</truncated><difficult>0</difficult><bndbox><xmin>111.0</xmin><ymin>42.66648000000001</ymin><xmax>161.99968</xmax><ymax>119.99976000000001</ymax></bndbox></object></annotations>