<annotations><filename>GH040011_239.jpg</filename><folder>images</folder><size><width>640</width><height>480</height><depth>3</depth></size><object><name>Person</name><pose>Unspecified</pose><truncated>0</truncated><difficult>0</difficult><bndbox><xmin>13.499839999999999</xmin><ymin>92.66639999999998</ymin><xmax>93.99968000000001</xmax><ymax>237.99983999999998</ymax></bndbox></object><object><name>Head</name><pose>Unspecified</pose><truncated>0</truncated><difficult>0</difficult><bndbox><xmin>17.99968</xmin><ymin>101.99976</ymin><xmax>43.99968</xmax><ymax>132.66648</ymax></bndbox></object><object><name>Body</name><pose>Unspecified</pose><truncated>0</truncated><difficult>0</difficult><bndbox><xmin>15.499839999999999</xmin><ymin>123.33312000000001</ymin><xmax>95.99968000000001</xmax><ymax>234.0</ymax></bndbox></object><object><name>Person</name><pose>Unspecified</pose><truncated>0</truncated><difficult>0</difficult><bndbox><xmin>0.0</xmin><ymin>138.66696</ymin><xmax>85.50016</xmax><ymax>274.66679999999997</ymax></bndbox></object><object><name>Head</name><pose>Unspecified</pose><truncated>0</truncated><difficult>0</difficult><bndbox><xmin>0.0</xmin><ymin>141.99984</ymin><xmax>18.49984</xmax><ymax>171.99984</ymax></bndbox></object><object><name>Body</name><pose>Unspecified</pose><truncated>0</truncated><difficult>0</difficult><bndbox><xmin>0.0</xmin><ymin>165.33312</ymin><xmax>80.0</xmax><ymax>270.0</ymax></bndbox></object></annotations>