<annotations><filename>GH040005_1594.jpg</filename><folder>images</folder><size><width>640</width><height>480</height><depth>3</depth></size><object><name>Person</name><pose>Unspecified</pose><truncated>0</truncated><difficult>0</difficult><bndbox><xmin>71.99968</xmin><ymin>111.33360000000002</ymin><xmax>131.49984</xmax><ymax>210.66672000000003</ymax></bndbox></object><object><name>Head</name><pose>Unspecified</pose><truncated>0</truncated><difficult>0</difficult><bndbox><xmin>82.50048</xmin><ymin>113.99999999999999</ymin><xmax>103.50016000000001</xmax><ymax>127.33343999999998</ymax></bndbox></object><object><name>Body</name><pose>Unspecified</pose><truncated>0</truncated><difficult>0</difficult><bndbox><xmin>77.00032</xmin><ymin>128.66639999999998</ymin><xmax>125.00032</xmax><ymax>201.99983999999998</ymax></bndbox></object></annotations>