<annotations><filename>GH040005_2244.jpg</filename><folder>images</folder><size><width>640</width><height>480</height><depth>3</depth></size><object><name>Person</name><pose>Unspecified</pose><truncated>0</truncated><difficult>0</difficult><bndbox><xmin>291.50016</xmin><ymin>36.00000000000001</ymin><xmax>332.49984</xmax><ymax>98.66688000000002</ymax></bndbox></object><object><name>Head</name><pose>Unspecified</pose><truncated>0</truncated><difficult>0</difficult><bndbox><xmin>301.50016</xmin><ymin>42.0</ymin><xmax>314.49984</xmax><ymax>64.66656</ymax></bndbox></object><object><name>Body</name><pose>Unspecified</pose><truncated>0</truncated><difficult>0</difficult><bndbox><xmin>310.99968</xmin><ymin>51.99983999999999</ymin><xmax>328.49984000000006</xmax><ymax>87.99983999999999</ymax></bndbox></object></annotations>